traceutils/__init__.py
traceutils/version.py
traceutils/alias/__init__.py
traceutils/alias/alias.py
traceutils/as2org/__init__.py
traceutils/as2org/as2org.c
traceutils/as2org/as2org.cpython-38-darwin.so
traceutils/as2org/as2org.pxd
traceutils/as2org/as2org.pyx
traceutils/bgp/__init__.py
traceutils/bgp/bgp.c
traceutils/bgp/bgp.cpython-38-darwin.so
traceutils/bgp/bgp.pxd
traceutils/bgp/bgp.pyx
traceutils/bgpreader/__init__.py
traceutils/bgpreader/reader.c
traceutils/bgpreader/reader.cpython-38-darwin.so
traceutils/bgpreader/reader.pxd
traceutils/bgpreader/reader.pyx
traceutils/file2/__init__.py
traceutils/file2/file2.c
traceutils/file2/file2.cpython-38-darwin.so
traceutils/file2/file2.pxd
traceutils/file2/file2.pyx
traceutils/ixps/__init__.py
traceutils/ixps/caida.py
traceutils/ixps/ixps.py
traceutils/ixps/peeringdb.py
traceutils/ixps/peeringdb_base.py
traceutils/ixps/peeringdb_v1.py
traceutils/progress/__init__.py
traceutils/progress/bar.c
traceutils/progress/bar.cpython-38-darwin.so
traceutils/progress/bar.py
traceutils/radix/__init__.py
traceutils/radix/ip2as.c
traceutils/radix/ip2as.cpython-38-darwin.so
traceutils/radix/ip2as.pxd
traceutils/radix/ip2as.pyx
traceutils/radix/ip2ases.c
traceutils/radix/ip2ases.cpython-38-darwin.so
traceutils/radix/ip2ases.pxd
traceutils/radix/ip2ases.pyx
traceutils/radix/ip2data.c
traceutils/radix/ip2data.cpython-38-darwin.so
traceutils/radix/ip2data.pxd
traceutils/radix/ip2data.pyx
traceutils/radix/radix.c
traceutils/radix/radix.cpython-38-darwin.so
traceutils/radix/radix.pxd
traceutils/radix/radix.pyx
traceutils/radix/radix_node.c
traceutils/radix/radix_node.cpython-38-darwin.so
traceutils/radix/radix_node.pxd
traceutils/radix/radix_node.pyx
traceutils/radix/radix_prefix.c
traceutils/radix/radix_prefix.cpython-38-darwin.so
traceutils/radix/radix_prefix.pxd
traceutils/radix/radix_prefix.pyx
traceutils/radix/radix_tree.c
traceutils/radix/radix_tree.cpython-38-darwin.so
traceutils/radix/radix_tree.pxd
traceutils/radix/radix_tree.pyx
traceutils-7.0.5.dist-info/METADATA
traceutils-7.0.5.dist-info/WHEEL
traceutils-7.0.5.dist-info/entry_points.txt
traceutils-7.0.5.dist-info/top_level.txt
traceutils-7.0.5.dist-info/RECORD
